{
  "add":[
    {
      "canonicalName": "001",
      "synonyms":["radiografia", "radiografía"],
      "nativeLanguageTag": "es"
    },
    {
      "canonicalName": "002",
      "synonyms":["mastografia", "mastografía"],
      "nativeLanguageTag": "es"
    }
  ],
  "delete":[
    {
      "canonicalName": "001",
      "nativeLanguageTag": "es"
    },
    {
      "canonicalName": "002",
      "nativeLanguageTag": "es"
    }
  ],
  "modify":[
    {
      "canonicalName": "001",
      "synonyms":["NUEVO_SINONIMO", "NUEVO_SINONIMO"],
      "nativeLanguageTag": "es"
    },
    {
      "canonicalName": "002",
      "synonyms":["NUEVO_SINONIMO", "NUEVO_SINONIMO"],
      "nativeLanguageTag": "es"
    }
  ]
}